terrafile/__init__.py
terrafile/__main__.py
terrafile-0.3.3.data/scripts/pterrafile
terrafile-0.3.3.dist-info/DESCRIPTION.rst
terrafile-0.3.3.dist-info/METADATA
terrafile-0.3.3.dist-info/RECORD
terrafile-0.3.3.dist-info/WHEEL
terrafile-0.3.3.dist-info/metadata.json
terrafile-0.3.3.dist-info/top_level.txt
