Metadata-Version: 2.0
Name: terrafile
Version: 0.3.3
Summary: Manages external Terraform modules.
Home-page: https://github.com/claranet/python-terrafile
Author: Raymond Butcher
Author-email: ray.butcher@claranet.uk
License: MIT License
Platform: UNKNOWN
Requires-Dist: pyyaml
Requires-Dist: requests
